<annotation>
	<folder>train</folder>
	<filename>mt74.jpg</filename>
	<path>C:\Users\merve\OneDrive\Masaüstü\olsunartık\train\mt74.jpg</path>
	<source>
		<database>Unknown</database>
	</source>
	<size>
		<width>1280</width>
		<height>720</height>
		<depth>3</depth>
	</size>
	<segmented>0</segmented>
	<object>
		<name>hand</name>
		<pose>Unspecified</pose>
		<truncated>0</truncated>
		<difficult>0</difficult>
		<bndbox>
			<xmin>594</xmin>
			<ymin>3</ymin>
			<xmax>733</xmax>
			<ymax>100</ymax>
		</bndbox>
	</object>
	<object>
		<name>hand</name>
		<pose>Unspecified</pose>
		<truncated>1</truncated>
		<difficult>0</difficult>
		<bndbox>
			<xmin>505</xmin>
			<ymin>596</ymin>
			<xmax>809</xmax>
			<ymax>720</ymax>
		</bndbox>
	</object>
</annotation>
