<annotation>
	<folder>train</folder>
	<filename>mt130.jpg</filename>
	<path>C:\Users\merve\OneDrive\Masaüstü\olsunartık\train\mt130.jpg</path>
	<source>
		<database>Unknown</database>
	</source>
	<size>
		<width>1600</width>
		<height>1200</height>
		<depth>3</depth>
	</size>
	<segmented>0</segmented>
	<object>
		<name>hand</name>
		<pose>Unspecified</pose>
		<truncated>0</truncated>
		<difficult>0</difficult>
		<bndbox>
			<xmin>425</xmin>
			<ymin>47</ymin>
			<xmax>1080</xmax>
			<ymax>1127</ymax>
		</bndbox>
	</object>
</annotation>
